{"nodes": [{"id": "app_samples_page", "label": "SamplesPage (app/samples/page.tsx)", "file_type": "code", "source_file": "app/samples/page.tsx", "source_location": null, "source_url": null, "captured_at": null, "author": null, "contributor": null}], "edges": [{"source": "app_samples_page", "target": "component_app_nav_buttons", "relation": "calls", "confidence": "EXTRACTED", "confidence_score": 1.0, "source_file": "app/samples/page.tsx", "source_location": null, "weight": 1.0}, {"source": "app_samples_page", "target": "component_clear_signup_verification_cookie", "relation": "calls", "confidence": "EXTRACTED", "confidence_score": 1.0, "source_file": "app/samples/page.tsx", "source_location": null, "weight": 1.0}, {"source": "app_samples_page", "target": "component_verification_error_toast", "relation": "calls", "confidence": "EXTRACTED", "confidence_score": 1.0, "source_file": "app/samples/page.tsx", "source_location": null, "weight": 1.0}, {"source": "app_samples_page", "target": "component_cart_drawer", "relation": "calls", "confidence": "EXTRACTED", "confidence_score": 1.0, "source_file": "app/samples/page.tsx", "source_location": null, "weight": 1.0}, {"source": "app_samples_page", "target": "component_sample_search", "relation": "calls", "confidence": "EXTRACTED", "confidence_score": 1.0, "source_file": "app/samples/page.tsx", "source_location": null, "weight": 1.0}, {"source": "app_samples_page", "target": "component_samples_list", "relation": "calls", "confidence": "EXTRACTED", "confidence_score": 1.0, "source_file": "app/samples/page.tsx", "source_location": null, "weight": 1.0}, {"source": "app_samples_page", "target": "lib_db", "relation": "calls", "confidence": "EXTRACTED", "confidence_score": 1.0, "source_file": "app/samples/page.tsx", "source_location": null, "weight": 1.0}, {"source": "app_samples_page", "target": "lib_fetch_samples", "relation": "calls", "confidence": "EXTRACTED", "confidence_score": 1.0, "source_file": "app/samples/page.tsx", "source_location": null, "weight": 1.0}, {"source": "app_samples_page", "target": "lib_get_query_client", "relation": "calls", "confidence": "EXTRACTED", "confidence_score": 1.0, "source_file": "app/samples/page.tsx", "source_location": null, "weight": 1.0}, {"source": "app_samples_page", "target": "lib_search_params_loaders", "relation": "calls", "confidence": "EXTRACTED", "confidence_score": 1.0, "source_file": "app/samples/page.tsx", "source_location": null, "weight": 1.0}], "hyperedges": []}